datasette_load/__init__.py
datasette_load/templates/load_view.html
datasette_load-0.1a5.dist-info/licenses/LICENSE
datasette_load-0.1a5.dist-info/METADATA
datasette_load-0.1a5.dist-info/WHEEL
datasette_load-0.1a5.dist-info/entry_points.txt
datasette_load-0.1a5.dist-info/top_level.txt
datasette_load-0.1a5.dist-info/RECORD
