Metadata-Version: 2.4
Name: datasette-load
Version: 0.1a5
Summary: API and UI for bulk loading data into Datasette from a URL
Author: Datasette
License-Expression: Apache-2.0
Project-URL: Homepage, https://github.com/datasette/datasette-load
Project-URL: Changelog, https://github.com/datasette/datasette-load/releases
Project-URL: Issues, https://github.com/datasette/datasette-load/issues
Project-URL: CI, https://github.com/datasette/datasette-load/actions
Classifier: Framework :: Datasette
Requires-Python: >=3.10
License-File: LICENSE
Requires-Dist: datasette>=1.0a21
Provides-Extra: test
Requires-Dist: pytest; extra == "test"
Requires-Dist: pytest-asyncio; extra == "test"
Requires-Dist: pytest-httpx; extra == "test"
Dynamic: license-file
